LICENSE
pygot/__init__.py
pygot/api/__init__.py
pygot/api/resources/__init__.py
pygot/api/resources/book.py
pygot/api/resources/character.py
pygot/api/resources/house.py
pygot/api/settings/__init__.py
pygot/models/__init__.py
pygot/models/book.py
pygot/models/character.py
pygot/models/house.py
pygot/pygot.py
pygot-0.2.0.dist-info/LICENSE
pygot-0.2.0.dist-info/WHEEL
pygot-0.2.0.dist-info/METADATA
pygot-0.2.0.dist-info/RECORD
